bear/__init__.py
bear/__main__.py
bear/common.py
bear/context.py
bear/hashing.py
bear/output.py
bear/tests/__init__.py
bear/tests/test_files.py
bear/tests/test_hash.py
bear/tests/test_main.py
thebear-0.6.0.data/data/bear/LICENSE.txt
thebear-0.6.0.data/data/bear/README.md
thebear-0.6.0.dist-info/LICENSE.txt
thebear-0.6.0.dist-info/METADATA
thebear-0.6.0.dist-info/WHEEL
thebear-0.6.0.dist-info/entry_points.txt
thebear-0.6.0.dist-info/top_level.txt
thebear-0.6.0.dist-info/RECORD
