Metadata-Version: 2.1
Name: thebear
Version: 0.6.0
Summary: Bear - the decluttering deduplicator
Home-page: https://github.com/KeyWeeUsr/Bear
Author: Peter Badida
Author-email: keyweeusr@gmail.com
License: UNKNOWN
Download-URL: https://github.com/KeyWeeUsr/Bear/zipball/0.6.0
Platform: UNKNOWN
Classifier: Development Status :: 4 - Beta
Classifier: License :: OSI Approved :: GNU Affero General Public License v3 or later (AGPLv3+)
Classifier: Operating System :: OS Independent
Classifier: Environment :: Console
Classifier: Intended Audience :: End Users/Desktop
Classifier: Intended Audience :: System Administrators
Classifier: Intended Audience :: Developers
Classifier: Natural Language :: English
Classifier: Programming Language :: Python
Classifier: Programming Language :: Python :: 3
Classifier: Programming Language :: Python :: 3.7
Classifier: Programming Language :: Python :: 3 :: Only
Classifier: Programming Language :: Python :: Implementation :: CPython
Classifier: Topic :: Utilities
Classifier: Typing :: Typed
Requires-Python: >=3.6
Requires-Dist: ensure
Provides-Extra: ci
Requires-Dist: coveralls ; extra == 'ci'
Provides-Extra: dev
Requires-Dist: pycodestyle ; extra == 'dev'
Requires-Dist: pylint ; extra == 'dev'
Requires-Dist: coverage ; extra == 'dev'
Requires-Dist: radon ; extra == 'dev'
Provides-Extra: dev_graph
Requires-Dist: pycodestyle ; extra == 'dev_graph'
Requires-Dist: pylint ; extra == 'dev_graph'
Requires-Dist: coverage ; extra == 'dev_graph'
Requires-Dist: radon ; extra == 'dev_graph'
Requires-Dist: wily ; extra == 'dev_graph'
Provides-Extra: release
Requires-Dist: pycodestyle ; extra == 'release'
Requires-Dist: pylint ; extra == 'release'
Requires-Dist: coverage ; extra == 'release'
Requires-Dist: radon ; extra == 'release'
Requires-Dist: coveralls ; extra == 'release'
Requires-Dist: setuptools ; extra == 'release'
Requires-Dist: wheel ; extra == 'release'
Requires-Dist: twine ; extra == 'release'
Requires-Dist: pyinstaller ; extra == 'release'
Requires-Dist: requests ; extra == 'release'
